<?xml version="1.0" encoding="UTF-8" standalone="yes"?><Club id="1"><amigos><socios id="2"><nombre>juan</nombre><direccion>calle perro</direccion><fechaAlta>01/03/2025</fechaAlta></socios><socios id="3"><nombre>miguel</nombre><direccion>calle porra</direccion><fechaAlta>12/03/2025</fechaAlta><amigos id="5"><nombre>antonio</nombre><direccion>calle porro</direccion><fechaAlta>16/03/2025</fechaAlta><amigos id="4"><nombre>luis</nombre><direccion>calle puerro</direccion><fechaAlta>20/03/2025</fechaAlta></amigos></amigos></socios><socios id="4"><nombre>luis</nombre><direccion>calle puerro</direccion><fechaAlta>20/03/2025</fechaAlta></socios><socios id="5"><nombre>antonio</nombre><direccion>calle porro</direccion><fechaAlta>16/03/2025</fechaAlta><amigos id="4"><nombre>luis</nombre><direccion>calle puerro</direccion><fechaAlta>20/03/2025</fechaAlta></amigos></socios></amigos></Club>